spatialmath_rospy/__init__.py
spatialmath_rospy/convert.py
spatialmath_rospy/monkey_patch_spatialmath.py
spatialmath_rospy/ros_compat_mixin.py
spatialmath_rospy-0.3.1.dist-info/LICENSE
spatialmath_rospy-0.3.1.dist-info/METADATA
spatialmath_rospy-0.3.1.dist-info/WHEEL
spatialmath_rospy-0.3.1.dist-info/top_level.txt
spatialmath_rospy-0.3.1.dist-info/RECORD
