Metadata-Version: 2.1
Name: spatialmath-rospy
Version: 0.3.1
Summary: spatialmath-python and rospy bridge library
Home-page: https://github.com/CallumJHays/spatialmath-rospy
Author: Callum J Hays
Author-email: callumjhays@gmail.com
License: MIT
Project-URL: Documentation, https://CallumJHays.github.io/spatialmath-rospy
Project-URL: Source, https://github.com/CallumJHays/spatialmath-rospy
Project-URL: Tracker, https://github.com/CallumJHays/spatialmath-rospy/issues
Project-URL: Coverage, https://codecov.io/gh/CallumJHays/spatialmath-rospy
Keywords: python ros rospy spatialmath spatialmath-python geometry robotics transformations
Platform: UNKNOWN
Classifier: Development Status :: 5 - Production/Stable
Classifier: Intended Audience :: Developers
Classifier: License :: OSI Approved :: MIT License
Classifier: Programming Language :: Python :: 3.6
Classifier: Programming Language :: Python :: 3.7
Classifier: Programming Language :: Python :: 3.8
Classifier: Programming Language :: Python :: 3.9
Classifier: Programming Language :: Python :: 3.10
Requires-Python: >=3.6
License-File: LICENSE
Requires-Dist: numpy
Requires-Dist: spatialmath-python
Requires-Dist: typing-extensions
Requires-Dist: pyyaml
Provides-Extra: dev
Requires-Dist: sympy ; extra == 'dev'
Requires-Dist: pytest ; extra == 'dev'
Requires-Dist: pytest-cov ; extra == 'dev'
Requires-Dist: coverage ; extra == 'dev'
Requires-Dist: codecov ; extra == 'dev'
Requires-Dist: recommonmark ; extra == 'dev'
Requires-Dist: flake8 ; extra == 'dev'
Requires-Dist: lark-parser ; extra == 'dev'
Provides-Extra: docs
Requires-Dist: sphinx ; extra == 'docs'
Requires-Dist: sphinx-tabs ; extra == 'docs'
Requires-Dist: sphinx-prompt ; extra == 'docs'
Requires-Dist: sphinx-toolbox ; extra == 'docs'
Requires-Dist: sphinx-rtd-theme ; extra == 'docs'
Requires-Dist: sphinx-autorun ; extra == 'docs'
Requires-Dist: sphinxcontrib-jsmath ; extra == 'docs'
Requires-Dist: sphinx-markdown-tables ; extra == 'docs'
Requires-Dist: myst-parser ; extra == 'docs'
Requires-Dist: sphinx-autodoc-typehints ; extra == 'docs'
